typegpt_moderation/__init__.py
typegpt_moderation/client.py
typegpt_moderation/models.py
typegpt_moderation-1.0.1.dist-info/METADATA
typegpt_moderation-1.0.1.dist-info/WHEEL
typegpt_moderation-1.0.1.dist-info/top_level.txt
typegpt_moderation-1.0.1.dist-info/RECORD
