Metadata-Version: 2.4
Name: typegpt-moderation
Version: 1.0.1
Summary: A client library for the TypeGPT Multimodal Moderation API.
Author: typegpt
Author-email: contact@typegpt.net
Classifier: Programming Language :: Python :: 3
Classifier: License :: OSI Approved :: MIT License
Classifier: Operating System :: OS Independent
Classifier: Intended Audience :: Developers
Classifier: Topic :: Software Development :: Libraries :: Python Modules
Classifier: Topic :: Security
Requires-Python: >=3.7
Requires-Dist: httpx>=0.20.0
Requires-Dist: pydantic>=2.0
Dynamic: author
Dynamic: author-email
Dynamic: classifier
Dynamic: description
Dynamic: description-content-type
Dynamic: requires-dist
Dynamic: requires-python
Dynamic: summary
